ylogging/__init__.py
ylogging/lib.py
ylogging-1.2.0.dist-info/LICENSE
ylogging-1.2.0.dist-info/METADATA
ylogging-1.2.0.dist-info/WHEEL
ylogging-1.2.0.dist-info/top_level.txt
ylogging-1.2.0.dist-info/RECORD
